odoo/addons/hr_calendar_multiweek/README.rst
odoo/addons/hr_calendar_multiweek/__init__.py
odoo/addons/hr_calendar_multiweek/__manifest__.py
odoo/addons/hr_calendar_multiweek/i18n/hr_calendar_multiweek.pot
odoo/addons/hr_calendar_multiweek/models/__init__.py
odoo/addons/hr_calendar_multiweek/models/resource_calendar.py
odoo/addons/hr_calendar_multiweek/readme/CONTRIBUTORS.rst
odoo/addons/hr_calendar_multiweek/readme/DESCRIPTION.rst
odoo/addons/hr_calendar_multiweek/readme/USAGE.rst
odoo/addons/hr_calendar_multiweek/static/description/icon.png
odoo/addons/hr_calendar_multiweek/static/description/index.html
odoo/addons/hr_calendar_multiweek/tests/__init__.py
odoo/addons/hr_calendar_multiweek/tests/test_resource_calendar.py
odoo/addons/hr_calendar_multiweek/views/resource_calendar.xml
odoo11_addon_hr_calendar_multiweek-11.0.1.0.0.99.dev3.dist-info/METADATA
odoo11_addon_hr_calendar_multiweek-11.0.1.0.0.99.dev3.dist-info/WHEEL
odoo11_addon_hr_calendar_multiweek-11.0.1.0.0.99.dev3.dist-info/top_level.txt
odoo11_addon_hr_calendar_multiweek-11.0.1.0.0.99.dev3.dist-info/RECORD
